sockpuppet/__init__.py
sockpuppet/cli.py
sockpuppet/ports.py
sockpuppet-0.2.2.dist-info/METADATA
sockpuppet-0.2.2.dist-info/WHEEL
sockpuppet-0.2.2.dist-info/entry_points.txt
sockpuppet-0.2.2.dist-info/top_level.txt
sockpuppet-0.2.2.dist-info/RECORD
