Metadata-Version: 2.1
Name: sockpuppet
Version: 0.2.2
Summary: Tools for integration tests involving real ports
Home-page: http://sockpuppet.readthedocs.org
Author: Chris Withers
Author-email: chris@withers.org
License: MIT
Platform: UNKNOWN
Classifier: Intended Audience :: Developers
Classifier: License :: OSI Approved :: MIT License
Classifier: Programming Language :: Python :: 2
Classifier: Programming Language :: Python :: 2.7
Classifier: Programming Language :: Python :: 3
Classifier: Programming Language :: Python :: 3.4
Classifier: Programming Language :: Python :: 3.5
Provides-Extra: build
Requires-Dist: sphinx ; extra == 'build'
Requires-Dist: pkginfo ; extra == 'build'
Requires-Dist: setuptools-git ; extra == 'build'
Provides-Extra: test
Requires-Dist: nose ; extra == 'test'
Requires-Dist: nose-cov ; extra == 'test'
Requires-Dist: nose-fixes ; extra == 'test'
Requires-Dist: testfixtures ; extra == 'test'
Requires-Dist: mock ; extra == 'test'
Requires-Dist: coveralls ; extra == 'test'
Requires-Dist: manuel ; extra == 'test'
